robocorp/tasks/__init__.py
robocorp/tasks/__main__.py
robocorp/tasks/_argdispatch.py
robocorp/tasks/_callback.py
robocorp/tasks/_collect_tasks.py
robocorp/tasks/_commands.py
robocorp/tasks/_config.py
robocorp/tasks/_constants.py
robocorp/tasks/_customization/__init__.py
robocorp/tasks/_customization/_extension_points.py
robocorp/tasks/_customization/_plugin_manager.py
robocorp/tasks/_exceptions.py
robocorp/tasks/_fixtures.py
robocorp/tasks/_hooks.py
robocorp/tasks/_interrupts.py
robocorp/tasks/_lifecycle.py
robocorp/tasks/_log_auto_setup.py
robocorp/tasks/_log_output_setup.py
robocorp/tasks/_protocols.py
robocorp/tasks/_remove_refs.py
robocorp/tasks/_task.py
robocorp/tasks/cli.py
robocorp/tasks/py.typed
robocorp_tasks-3.1.0.dist-info/METADATA
robocorp_tasks-3.1.0.dist-info/WHEEL
robocorp_tasks-3.1.0.dist-info/RECORD
