Metadata-Version: 2.1
Name: robocorp-tasks
Version: 3.1.0
Summary: The automation framework for Python
Home-page: https://github.com/robocorp/robocorp/
License: Apache-2.0
Author: Fabio Z.
Author-email: fabio@robocorp.com
Requires-Python: >=3.9,<4.0
Classifier: Development Status :: 5 - Production/Stable
Classifier: License :: OSI Approved :: Apache Software License
Classifier: Programming Language :: Python :: 3
Classifier: Programming Language :: Python :: 3.9
Classifier: Programming Language :: Python :: 3.10
Classifier: Programming Language :: Python :: 3.11
Classifier: Programming Language :: Python :: 3.12
Classifier: Topic :: Software Development :: Libraries :: Application Frameworks
Requires-Dist: docstring_parser_fork (>=0.0.5,<0.0.6)
Requires-Dist: packaging (>=24.0,<25.0)
Requires-Dist: psutil (>=5.0,<6.0)
Requires-Dist: robocorp-log (>=2.4,<3)
Project-URL: Repository, https://github.com/robocorp/robocorp/
